momtag/artwork.py
momtag/library.py
momtag/momtag.py
momtag/track.py
momtag-0.1.1.dist-info/METADATA
momtag-0.1.1.dist-info/WHEEL
momtag-0.1.1.dist-info/entry_points.txt
momtag-0.1.1.dist-info/licenses/LICENSES/CC-BY-4.0.txt
momtag-0.1.1.dist-info/licenses/LICENSES/GPL-3.0-or-later.txt
momtag-0.1.1.dist-info/RECORD
