Metadata-Version: 2.4
Name: momtag
Version: 0.1.1
Summary: Mike's Opinionated Music Tagger
Project-URL: Homepage, https://codeberg.org/MikeCoats/momtag
Project-URL: Repository, https://codeberg.org/MikeCoats/momtag.git
Project-URL: Issues, https://codeberg.org/MikeCoats/momtag/issues
Author-email: Mike Coats <i.am@mikecoats.com>
License-Expression: GPL-3.0-or-later
License-File: LICENSES/CC-BY-4.0.txt
License-File: LICENSES/GPL-3.0-or-later.txt
Classifier: Development Status :: 3 - Alpha
Classifier: Environment :: Console
Classifier: Intended Audience :: End Users/Desktop
Classifier: License :: OSI Approved :: GNU General Public License v3 or later (GPLv3+)
Classifier: Natural Language :: English
Classifier: Programming Language :: Python :: 3
Classifier: Topic :: Multimedia :: Sound/Audio
Classifier: Topic :: Multimedia :: Sound/Audio :: Conversion
Classifier: Topic :: Multimedia :: Sound/Audio :: Editors
Classifier: Topic :: System :: Archiving
Classifier: Topic :: Utilities
Requires-Python: >=3.11
Requires-Dist: click~=8.3.1
Requires-Dist: mutagen~=1.47.0
Requires-Dist: pillow~=12.0.0
Provides-Extra: optional
Requires-Dist: build~=1.3.0; extra == 'optional'
Requires-Dist: pyfakefs~=5.10.2; extra == 'optional'
Requires-Dist: pytest~=9.0.1; extra == 'optional'
Requires-Dist: reuse~=6.2.0; extra == 'optional'
Requires-Dist: ruff~=0.14.5; extra == 'optional'
Requires-Dist: twine~=6.2.0; extra == 'optional'
Requires-Dist: ty~=0.0.1a31; extra == 'optional'
